mention/__init__.py
mention/base.py
mention/exceptions.py
mention/utils.py
mention-0.1.dist-info/LICENSE
mention-0.1.dist-info/METADATA
mention-0.1.dist-info/WHEEL
mention-0.1.dist-info/top_level.txt
mention-0.1.dist-info/RECORD
