Metadata-Version: 2.1
Name: mention
Version: 0.1
Summary: A Python wrapper around the Mention API.
Home-page: https://github.com/mazi76erX2/mention-python
Author: Xolani Mazibuko
Author-email: mazi76erx@gmail.com
License: UNKNOWN
Project-URL: Coverage, https://codecov.io/gh/mazi76erX2/mention-python
Project-URL: Documentation, https://mention-python.readthedocs.io/en/latest/
Project-URL: Source Code, https://github.com/mazi76erX2/mention-python
Keywords: mention api examples
Platform: UNKNOWN
Classifier: Environment :: Web Environment
Classifier: Intended Audience :: Developers
Classifier: Operating System :: OS Independent
Classifier: Programming Language :: Python :: 3
Classifier: License :: OSI Approved :: MIT License
Requires-Dist: requests
Requires-Dist: requests-oauth2 (>=0.3.0)
